sigrokdecode/__init__.py
sigrokdecode/bits.py
sigrokdecode/cli.py
sigrokdecode/input.py
sigrokdecode/output.py
sigrokdecode/runtc.py
sigrokdecode/srzip.py
pysigrok-0.4.2.dist-info/entry_points.txt
pysigrok-0.4.2.dist-info/LICENSE
pysigrok-0.4.2.dist-info/WHEEL
pysigrok-0.4.2.dist-info/METADATA
pysigrok-0.4.2.dist-info/RECORD
